{
  "version": "1.0",
  "generated": "2026-01-17",
  "settings": [
    {
      "category": "System",
      "key": "Core.Theme",
      "displayName": "Application Theme",
      "defaultValue": "System",
      "dataType": "String",
      "scope": "System",
      "permissionLevel": "User",
      "isSensitive": false,
      "validationRules": "Allowed: Light, Dark, System"
    },
    {
      "category": "System",
      "key": "Core.Logging.Level",
      "displayName": "Logging Level",
      "defaultValue": "Information",
      "dataType": "String",
      "scope": "System",
      "permissionLevel": "User",
      "isSensitive": false,
      "validationRules": "Allowed: Verbose, Debug, Information, Warning, Error, Fatal"
    },
    {
      "category": "System",
      "key": "Core.Database.StoredProcedureMaxRetries",
      "displayName": "Stored Procedure Max Retries",
      "defaultValue": "3",
      "dataType": "Int",
      "scope": "System",
      "permissionLevel": "Developer",
      "isSensitive": false,
      "validationRules": "Range: 0-10"
    },
    {
      "category": "User",
      "key": "Core.UI.CompactMode",
      "displayName": "Compact Mode",
      "defaultValue": "false",
      "dataType": "Bool",
      "scope": "User",
      "permissionLevel": "User",
      "isSensitive": false,
      "validationRules": "Boolean"
    },
    {
      "category": "System",
      "key": "Core.SharedPaths.ExportRoot",
      "displayName": "Export Root Path",
      "defaultValue": "C:/MTM/Exports",
      "dataType": "String",
      "scope": "System",
      "permissionLevel": "User",
      "isSensitive": false,
      "validationRules": "Path"
    },
    {
      "category": "System",
      "key": "Core.Database.ConnectionSecret",
      "displayName": "Database Connection Secret",
      "defaultValue": "",
      "dataType": "String",
      "scope": "System",
      "permissionLevel": "User",
      "isSensitive": true,
      "validationRules": "Sensitive"
    },
    {
      "category": "Receiving",
      "key": "Receiving.UiText.ModeSelection.GuidedTitle",
      "displayName": "Mode Selection - Guided Title",
      "defaultValue": "Guided Wizard",
      "dataType": "String",
      "scope": "System",
      "permissionLevel": "User",
      "isSensitive": false,
      "validationRules": "String"
    },
    {
      "category": "Receiving",
      "key": "Receiving.UiText.ModeSelection.GuidedDescription",
      "displayName": "Mode Selection - Guided Description",
      "defaultValue": "Step-by-step process for standard receiving workflow.",
      "dataType": "String",
      "scope": "System",
      "permissionLevel": "User",
      "isSensitive": false,
      "validationRules": "String"
    },
    {
      "category": "Receiving",
      "key": "Receiving.UiText.ModeSelection.ManualTitle",
      "displayName": "Mode Selection - Manual Title",
      "defaultValue": "Manual Entry",
      "dataType": "String",
      "scope": "System",
      "permissionLevel": "User",
      "isSensitive": false,
      "validationRules": "String"
    },
    {
      "category": "Receiving",
      "key": "Receiving.UiText.ModeSelection.ManualDescription",
      "displayName": "Mode Selection - Manual Description",
      "defaultValue": "Customizable grid for bulk data entry and editing.",
      "dataType": "String",
      "scope": "System",
      "permissionLevel": "User",
      "isSensitive": false,
      "validationRules": "String"
    },
    {
      "category": "Receiving",
      "key": "Receiving.UiText.ModeSelection.EditTitle",
      "displayName": "Mode Selection - Edit Title",
      "defaultValue": "Edit Mode",
      "dataType": "String",
      "scope": "System",
      "permissionLevel": "User",
      "isSensitive": false,
      "validationRules": "String"
    },
    {
      "category": "Receiving",
      "key": "Receiving.UiText.ModeSelection.EditDescription",
      "displayName": "Mode Selection - Edit Description",
      "defaultValue": "Edit existing loads without adding new ones.",
      "dataType": "String",
      "scope": "System",
      "permissionLevel": "User",
      "isSensitive": false,
      "validationRules": "String"
    },
    {
      "category": "Receiving",
      "key": "Receiving.UiText.ModeSelection.SetDefault",
      "displayName": "Mode Selection - Set Default",
      "defaultValue": "Set as default mode",
      "dataType": "String",
      "scope": "System",
      "permissionLevel": "User",
      "isSensitive": false,
      "validationRules": "String"
    },
    {
      "category": "Receiving",
      "key": "Receiving.UiText.Workflow.Help",
      "displayName": "Workflow - Help Button",
      "defaultValue": "Help",
      "dataType": "String",
      "scope": "System",
      "permissionLevel": "User",
      "isSensitive": false,
      "validationRules": "String"
    },
    {
      "category": "Receiving",
      "key": "Receiving.UiText.Workflow.Back",
      "displayName": "Workflow - Back Button",
      "defaultValue": "Back",
      "dataType": "String",
      "scope": "System",
      "permissionLevel": "User",
      "isSensitive": false,
      "validationRules": "String"
    },
    {
      "category": "Receiving",
      "key": "Receiving.UiText.Workflow.Next",
      "displayName": "Workflow - Next Button",
      "defaultValue": "Next",
      "dataType": "String",
      "scope": "System",
      "permissionLevel": "User",
      "isSensitive": false,
      "validationRules": "String"
    },
    {
      "category": "Receiving",
      "key": "Receiving.UiText.Workflow.ModeSelection",
      "displayName": "Workflow - Mode Selection Button",
      "defaultValue": "Mode Selection",
      "dataType": "String",
      "scope": "System",
      "permissionLevel": "User",
      "isSensitive": false,
      "validationRules": "String"
    },
    {
      "category": "Receiving",
      "key": "Receiving.UiText.Workflow.ResetCsv",
      "displayName": "Workflow - Reset CSV Button",
      "defaultValue": "Reset CSV",
      "dataType": "String",
      "scope": "System",
      "permissionLevel": "User",
      "isSensitive": false,
      "validationRules": "String"
    },
    {
      "category": "Receiving",
      "key": "Receiving.UiText.Completion.SuccessTitle",
      "displayName": "Completion - Success Title",
      "defaultValue": "Success!",
      "dataType": "String",
      "scope": "System",
      "permissionLevel": "User",
      "isSensitive": false,
      "validationRules": "String"
    },
    {
      "category": "Receiving",
      "key": "Receiving.UiText.Completion.FailureTitle",
      "displayName": "Completion - Failure Title",
      "defaultValue": "Save Failed",
      "dataType": "String",
      "scope": "System",
      "permissionLevel": "User",
      "isSensitive": false,
      "validationRules": "String"
    },
    {
      "category": "Receiving",
      "key": "Receiving.UiText.Completion.LoadsSavedSuffix",
      "displayName": "Completion - Loads Saved Suffix",
      "defaultValue": " loads saved successfully.",
      "dataType": "String",
      "scope": "System",
      "permissionLevel": "User",
      "isSensitive": false,
      "validationRules": "String"
    },
    {
      "category": "Receiving",
      "key": "Receiving.UiText.Completion.SaveDetailsTitle",
      "displayName": "Completion - Save Details Title",
      "defaultValue": "Save Details:",
      "dataType": "String",
      "scope": "System",
      "permissionLevel": "User",
      "isSensitive": false,
      "validationRules": "String"
    },
    {
      "category": "Receiving",
      "key": "Receiving.UiText.Completion.LocalCsvLabel",
      "displayName": "Completion - Local CSV Label",
      "defaultValue": "Local CSV:",
      "dataType": "String",
      "scope": "System",
      "permissionLevel": "User",
      "isSensitive": false,
      "validationRules": "String"
    },
    {
      "category": "Receiving",
      "key": "Receiving.UiText.Completion.NetworkCsvLabel",
      "displayName": "Completion - Network CSV Label",
      "defaultValue": "Network CSV:",
      "dataType": "String",
      "scope": "System",
      "permissionLevel": "User",
      "isSensitive": false,
      "validationRules": "String"
    },
    {
      "category": "Receiving",
      "key": "Receiving.UiText.Completion.DatabaseLabel",
      "displayName": "Completion - Database Label",
      "defaultValue": "Database:",
      "dataType": "String",
      "scope": "System",
      "permissionLevel": "User",
      "isSensitive": false,
      "validationRules": "String"
    },
    {
      "category": "Receiving",
      "key": "Receiving.UiText.Completion.Saved",
      "displayName": "Completion - Saved Status",
      "defaultValue": "Saved",
      "dataType": "String",
      "scope": "System",
      "permissionLevel": "User",
      "isSensitive": false,
      "validationRules": "String"
    },
    {
      "category": "Receiving",
      "key": "Receiving.UiText.Completion.Failed",
      "displayName": "Completion - Failed Status",
      "defaultValue": "Failed",
      "dataType": "String",
      "scope": "System",
      "permissionLevel": "User",
      "isSensitive": false,
      "validationRules": "String"
    },
    {
      "category": "Receiving",
      "key": "Receiving.UiText.Completion.StartNewEntry",
      "displayName": "Completion - Start New Entry Button",
      "defaultValue": "Start New Entry",
      "dataType": "String",
      "scope": "System",
      "permissionLevel": "User",
      "isSensitive": false,
      "validationRules": "String"
    },
    {
      "category": "Receiving",
      "key": "Receiving.UiText.ManualEntry.AddRow",
      "displayName": "Manual Entry - Add Row",
      "defaultValue": "Add Row",
      "dataType": "String",
      "scope": "System",
      "permissionLevel": "User",
      "isSensitive": false,
      "validationRules": "String"
    },
    {
      "category": "Receiving",
      "key": "Receiving.UiText.ManualEntry.AddMultiple",
      "displayName": "Manual Entry - Add Multiple",
      "defaultValue": "Add Multiple",
      "dataType": "String",
      "scope": "System",
      "permissionLevel": "User",
      "isSensitive": false,
      "validationRules": "String"
    },
    {
      "category": "Receiving",
      "key": "Receiving.UiText.ManualEntry.RemoveRow",
      "displayName": "Manual Entry - Remove Row",
      "defaultValue": "Remove Row",
      "dataType": "String",
      "scope": "System",
      "permissionLevel": "User",
      "isSensitive": false,
      "validationRules": "String"
    },
    {
      "category": "Receiving",
      "key": "Receiving.UiText.ManualEntry.AutoFill",
      "displayName": "Manual Entry - Auto-Fill",
      "defaultValue": "Auto-Fill",
      "dataType": "String",
      "scope": "System",
      "permissionLevel": "User",
      "isSensitive": false,
      "validationRules": "String"
    },
    {
      "category": "Receiving",
      "key": "Receiving.UiText.ManualEntry.SaveAndFinish",
      "displayName": "Manual Entry - Save & Finish",
      "defaultValue": "Save & Finish",
      "dataType": "String",
      "scope": "System",
      "permissionLevel": "User",
      "isSensitive": false,
      "validationRules": "String"
    },
    {
      "category": "Receiving",
      "key": "Receiving.UiText.ManualEntry.Column.LoadNumber",
      "displayName": "Manual Entry - Load # Column",
      "defaultValue": "Load #",
      "dataType": "String",
      "scope": "System",
      "permissionLevel": "User",
      "isSensitive": false,
      "validationRules": "String"
    },
    {
      "category": "Receiving",
      "key": "Receiving.UiText.ManualEntry.Column.PartId",
      "displayName": "Manual Entry - Part ID Column",
      "defaultValue": "Part ID",
      "dataType": "String",
      "scope": "System",
      "permissionLevel": "User",
      "isSensitive": false,
      "validationRules": "String"
    },
    {
      "category": "Receiving",
      "key": "Receiving.UiText.ManualEntry.Column.WeightQty",
      "displayName": "Manual Entry - Weight/Qty Column",
      "defaultValue": "Weight/Qty",
      "dataType": "String",
      "scope": "System",
      "permissionLevel": "User",
      "isSensitive": false,
      "validationRules": "String"
    },
    {
      "category": "Receiving",
      "key": "Receiving.UiText.ManualEntry.Column.HeatLot",
      "displayName": "Manual Entry - Heat/Lot Column",
      "defaultValue": "Heat/Lot",
      "dataType": "String",
      "scope": "System",
      "permissionLevel": "User",
      "isSensitive": false,
      "validationRules": "String"
    },
    {
      "category": "Receiving",
      "key": "Receiving.UiText.ManualEntry.Column.PkgType",
      "displayName": "Manual Entry - Pkg Type Column",
      "defaultValue": "Pkg Type",
      "dataType": "String",
      "scope": "System",
      "permissionLevel": "User",
      "isSensitive": false,
      "validationRules": "String"
    },
    {
      "category": "Receiving",
      "key": "Receiving.UiText.ManualEntry.Column.PkgsPerLoad",
      "displayName": "Manual Entry - Pkgs/Load Column",
      "defaultValue": "Pkgs/Load",
      "dataType": "String",
      "scope": "System",
      "permissionLevel": "User",
      "isSensitive": false,
      "validationRules": "String"
    },
    {
      "category": "Receiving",
      "key": "Receiving.UiText.ManualEntry.Column.WtPerPkg",
      "displayName": "Manual Entry - Wt/Pkg Column",
      "defaultValue": "Wt/Pkg",
      "dataType": "String",
      "scope": "System",
      "permissionLevel": "User",
      "isSensitive": false,
      "validationRules": "String"
    },
    {
      "category": "Receiving",
      "key": "Receiving.UiText.EditMode.LoadDataFrom",
      "displayName": "Edit Mode - Load Data From",
      "defaultValue": "Load Data From:",
      "dataType": "String",
      "scope": "System",
      "permissionLevel": "User",
      "isSensitive": false,
      "validationRules": "String"
    },
    {
      "category": "Receiving",
      "key": "Receiving.UiText.EditMode.CurrentMemory",
      "displayName": "Edit Mode - Current Memory",
      "defaultValue": "Current Memory",
      "dataType": "String",
      "scope": "System",
      "permissionLevel": "User",
      "isSensitive": false,
      "validationRules": "String"
    },
    {
      "category": "Receiving",
      "key": "Receiving.UiText.EditMode.CurrentLabels",
      "displayName": "Edit Mode - Current Labels",
      "defaultValue": "Current Labels",
      "dataType": "String",
      "scope": "System",
      "permissionLevel": "User",
      "isSensitive": false,
      "validationRules": "String"
    },
    {
      "category": "Receiving",
      "key": "Receiving.UiText.EditMode.History",
      "displayName": "Edit Mode - History",
      "defaultValue": "History",
      "dataType": "String",
      "scope": "System",
      "permissionLevel": "User",
      "isSensitive": false,
      "validationRules": "String"
    },
    {
      "category": "Receiving",
      "key": "Receiving.UiText.EditMode.FilterDate",
      "displayName": "Edit Mode - Filter Date",
      "defaultValue": "Filter Date:",
      "dataType": "String",
      "scope": "System",
      "permissionLevel": "User",
      "isSensitive": false,
      "validationRules": "String"
    },
    {
      "category": "Receiving",
      "key": "Receiving.UiText.EditMode.To",
      "displayName": "Edit Mode - To",
      "defaultValue": "to",
      "dataType": "String",
      "scope": "System",
      "permissionLevel": "User",
      "isSensitive": false,
      "validationRules": "String"
    },
    {
      "category": "Receiving",
      "key": "Receiving.UiText.EditMode.LastWeek",
      "displayName": "Edit Mode - Last Week",
      "defaultValue": "Last Week",
      "dataType": "String",
      "scope": "System",
      "permissionLevel": "User",
      "isSensitive": false,
      "validationRules": "String"
    },
    {
      "category": "Receiving",
      "key": "Receiving.UiText.EditMode.Today",
      "displayName": "Edit Mode - Today",
      "defaultValue": "Today",
      "dataType": "String",
      "scope": "System",
      "permissionLevel": "User",
      "isSensitive": false,
      "validationRules": "String"
    },
    {
      "category": "Receiving",
      "key": "Receiving.UiText.EditMode.ThisWeek",
      "displayName": "Edit Mode - This Week",
      "defaultValue": "This Week",
      "dataType": "String",
      "scope": "System",
      "permissionLevel": "User",
      "isSensitive": false,
      "validationRules": "String"
    },
    {
      "category": "Receiving",
      "key": "Receiving.UiText.EditMode.ShowAll",
      "displayName": "Edit Mode - Show All",
      "defaultValue": "Show All",
      "dataType": "String",
      "scope": "System",
      "permissionLevel": "User",
      "isSensitive": false,
      "validationRules": "String"
    },
    {
      "category": "Receiving",
      "key": "Receiving.UiText.EditMode.Page",
      "displayName": "Edit Mode - Page",
      "defaultValue": "Page",
      "dataType": "String",
      "scope": "System",
      "permissionLevel": "User",
      "isSensitive": false,
      "validationRules": "String"
    },
    {
      "category": "Receiving",
      "key": "Receiving.UiText.EditMode.Of",
      "displayName": "Edit Mode - Of",
      "defaultValue": "of",
      "dataType": "String",
      "scope": "System",
      "permissionLevel": "User",
      "isSensitive": false,
      "validationRules": "String"
    },
    {
      "category": "Receiving",
      "key": "Receiving.UiText.EditMode.Go",
      "displayName": "Edit Mode - Go",
      "defaultValue": "Go",
      "dataType": "String",
      "scope": "System",
      "permissionLevel": "User",
      "isSensitive": false,
      "validationRules": "String"
    },
    {
      "category": "Receiving",
      "key": "Receiving.UiText.EditMode.SaveAndFinish",
      "displayName": "Edit Mode - Save & Finish",
      "defaultValue": "Save & Finish",
      "dataType": "String",
      "scope": "System",
      "permissionLevel": "User",
      "isSensitive": false,
      "validationRules": "String"
    },
    {
      "category": "Receiving",
      "key": "Receiving.UiText.EditMode.RemoveRow",
      "displayName": "Edit Mode - Remove Row",
      "defaultValue": "Remove Row",
      "dataType": "String",
      "scope": "System",
      "permissionLevel": "User",
      "isSensitive": false,
      "validationRules": "String"
    },
    {
      "category": "Receiving",
      "key": "Receiving.UiText.EditMode.Column.LoadNumber",
      "displayName": "Edit Mode - Load # Column",
      "defaultValue": "Load #",
      "dataType": "String",
      "scope": "System",
      "permissionLevel": "User",
      "isSensitive": false,
      "validationRules": "String"
    },
    {
      "category": "Receiving",
      "key": "Receiving.UiText.EditMode.Column.PartId",
      "displayName": "Edit Mode - Part ID Column",
      "defaultValue": "Part ID",
      "dataType": "String",
      "scope": "System",
      "permissionLevel": "User",
      "isSensitive": false,
      "validationRules": "String"
    },
    {
      "category": "Receiving",
      "key": "Receiving.UiText.EditMode.Column.WeightQty",
      "displayName": "Edit Mode - Weight/Qty Column",
      "defaultValue": "Weight/Qty",
      "dataType": "String",
      "scope": "System",
      "permissionLevel": "User",
      "isSensitive": false,
      "validationRules": "String"
    },
    {
      "category": "Receiving",
      "key": "Receiving.UiText.EditMode.Column.HeatLot",
      "displayName": "Edit Mode - Heat/Lot Column",
      "defaultValue": "Heat/Lot",
      "dataType": "String",
      "scope": "System",
      "permissionLevel": "User",
      "isSensitive": false,
      "validationRules": "String"
    },
    {
      "category": "Receiving",
      "key": "Receiving.UiText.EditMode.Column.PkgType",
      "displayName": "Edit Mode - Pkg Type Column",
      "defaultValue": "Pkg Type",
      "dataType": "String",
      "scope": "System",
      "permissionLevel": "User",
      "isSensitive": false,
      "validationRules": "String"
    },
    {
      "category": "Receiving",
      "key": "Receiving.UiText.EditMode.Column.PkgsPerLoad",
      "displayName": "Edit Mode - Pkgs/Load Column",
      "defaultValue": "Pkgs/Load",
      "dataType": "String",
      "scope": "System",
      "permissionLevel": "User",
      "isSensitive": false,
      "validationRules": "String"
    },
    {
      "category": "Receiving",
      "key": "Receiving.UiText.EditMode.Column.WtPerPkg",
      "displayName": "Edit Mode - Wt/Pkg Column",
      "defaultValue": "Wt/Pkg",
      "dataType": "String",
      "scope": "System",
      "permissionLevel": "User",
      "isSensitive": false,
      "validationRules": "String"
    },
    {
      "category": "Receiving",
      "key": "Receiving.UiText.PoEntry.PurchaseOrderNumber",
      "displayName": "PO Entry - Purchase Order Number",
      "defaultValue": "Purchase Order Number",
      "dataType": "String",
      "scope": "System",
      "permissionLevel": "User",
      "isSensitive": false,
      "validationRules": "String"
    },
    {
      "category": "Receiving",
      "key": "Receiving.UiText.PoEntry.StatusLabel",
      "displayName": "PO Entry - Status Label",
      "defaultValue": "Status:",
      "dataType": "String",
      "scope": "System",
      "permissionLevel": "User",
      "isSensitive": false,
      "validationRules": "String"
    },
    {
      "category": "Receiving",
      "key": "Receiving.UiText.PoEntry.LoadPo",
      "displayName": "PO Entry - Load PO",
      "defaultValue": "Load PO",
      "dataType": "String",
      "scope": "System",
      "permissionLevel": "User",
      "isSensitive": false,
      "validationRules": "String"
    },
    {
      "category": "Receiving",
      "key": "Receiving.UiText.PoEntry.SwitchToNonPo",
      "displayName": "PO Entry - Switch to Non-PO",
      "defaultValue": "Switch to Non-PO",
      "dataType": "String",
      "scope": "System",
      "permissionLevel": "User",
      "isSensitive": false,
      "validationRules": "String"
    },
    {
      "category": "Receiving",
      "key": "Receiving.UiText.PoEntry.PartIdentifier",
      "displayName": "PO Entry - Part Identifier",
      "defaultValue": "Part Identifier",
      "dataType": "String",
      "scope": "System",
      "permissionLevel": "User",
      "isSensitive": false,
      "validationRules": "String"
    },
    {
      "category": "Receiving",
      "key": "Receiving.UiText.PoEntry.PackageTypeAuto",
      "displayName": "PO Entry - Package Type Auto",
      "defaultValue": "Package Type (Auto-detected)",
      "dataType": "String",
      "scope": "System",
      "permissionLevel": "User",
      "isSensitive": false,
      "validationRules": "String"
    },
    {
      "category": "Receiving",
      "key": "Receiving.UiText.PoEntry.LookupPart",
      "displayName": "PO Entry - Look Up Part",
      "defaultValue": "Look Up Part",
      "dataType": "String",
      "scope": "System",
      "permissionLevel": "User",
      "isSensitive": false,
      "validationRules": "String"
    },
    {
      "category": "Receiving",
      "key": "Receiving.UiText.PoEntry.SwitchToPo",
      "displayName": "PO Entry - Switch to PO",
      "defaultValue": "Switch to PO Entry",
      "dataType": "String",
      "scope": "System",
      "permissionLevel": "User",
      "isSensitive": false,
      "validationRules": "String"
    },
    {
      "category": "Receiving",
      "key": "Receiving.UiText.PoEntry.AvailableParts",
      "displayName": "PO Entry - Available Parts",
      "defaultValue": "Available Parts",
      "dataType": "String",
      "scope": "System",
      "permissionLevel": "User",
      "isSensitive": false,
      "validationRules": "String"
    },
    {
      "category": "Receiving",
      "key": "Receiving.UiText.PoEntry.Column.PartId",
      "displayName": "PO Entry - Part ID Column",
      "defaultValue": "Part ID",
      "dataType": "String",
      "scope": "System",
      "permissionLevel": "User",
      "isSensitive": false,
      "validationRules": "String"
    },
    {
      "category": "Receiving",
      "key": "Receiving.UiText.PoEntry.Column.Description",
      "displayName": "PO Entry - Description Column",
      "defaultValue": "Description",
      "dataType": "String",
      "scope": "System",
      "permissionLevel": "User",
      "isSensitive": false,
      "validationRules": "String"
    },
    {
      "category": "Receiving",
      "key": "Receiving.UiText.PoEntry.Column.RemainingQty",
      "displayName": "PO Entry - Remaining Qty Column",
      "defaultValue": "Remaining Qty",
      "dataType": "String",
      "scope": "System",
      "permissionLevel": "User",
      "isSensitive": false,
      "validationRules": "String"
    },
    {
      "category": "Receiving",
      "key": "Receiving.UiText.PoEntry.Column.QtyOrdered",
      "displayName": "PO Entry - Qty Ordered Column",
      "defaultValue": "Qty Ordered",
      "dataType": "String",
      "scope": "System",
      "permissionLevel": "User",
      "isSensitive": false,
      "validationRules": "String"
    },
    {
      "category": "Receiving",
      "key": "Receiving.UiText.PoEntry.Column.LineNumber",
      "displayName": "PO Entry - Line # Column",
      "defaultValue": "Line #",
      "dataType": "String",
      "scope": "System",
      "permissionLevel": "User",
      "isSensitive": false,
      "validationRules": "String"
    },
    {
      "category": "Receiving",
      "key": "Receiving.UiText.LoadEntry.Header",
      "displayName": "Load Entry - Header",
      "defaultValue": "Number of Loads (1-99)",
      "dataType": "String",
      "scope": "System",
      "permissionLevel": "User",
      "isSensitive": false,
      "validationRules": "String"
    },
    {
      "category": "Receiving",
      "key": "Receiving.UiText.LoadEntry.Instruction",
      "displayName": "Load Entry - Instruction",
      "defaultValue": "Enter the total number of skids/loads for this part.",
      "dataType": "String",
      "scope": "System",
      "permissionLevel": "User",
      "isSensitive": false,
      "validationRules": "String"
    },
    {
      "category": "Receiving",
      "key": "Receiving.UiText.WeightQuantity.Header",
      "displayName": "Weight/Quantity - Header",
      "defaultValue": "Weight/Quantity",
      "dataType": "String",
      "scope": "System",
      "permissionLevel": "User",
      "isSensitive": false,
      "validationRules": "String"
    },
    {
      "category": "Receiving",
      "key": "Receiving.UiText.WeightQuantity.Placeholder",
      "displayName": "Weight/Quantity - Placeholder",
      "defaultValue": "Enter whole number",
      "dataType": "String",
      "scope": "System",
      "permissionLevel": "User",
      "isSensitive": false,
      "validationRules": "String"
    },
    {
      "category": "Receiving",
      "key": "Receiving.UiText.HeatLot.Header",
      "displayName": "Heat/Lot - Header",
      "defaultValue": "Load Entries",
      "dataType": "String",
      "scope": "System",
      "permissionLevel": "User",
      "isSensitive": false,
      "validationRules": "String"
    },
    {
      "category": "Receiving",
      "key": "Receiving.UiText.HeatLot.AutoFill",
      "displayName": "Heat/Lot - Auto-Fill",
      "defaultValue": "Auto-Fill",
      "dataType": "String",
      "scope": "System",
      "permissionLevel": "User",
      "isSensitive": false,
      "validationRules": "String"
    },
    {
      "category": "Receiving",
      "key": "Receiving.UiText.HeatLot.AutoFillTooltip",
      "displayName": "Heat/Lot - Auto-Fill Tooltip",
      "defaultValue": "Fill blank heat numbers from rows above",
      "dataType": "String",
      "scope": "System",
      "permissionLevel": "User",
      "isSensitive": false,
      "validationRules": "String"
    },
    {
      "category": "Receiving",
      "key": "Receiving.UiText.HeatLot.LoadPrefix",
      "displayName": "Heat/Lot - Load Prefix",
      "defaultValue": "Load #{0}",
      "dataType": "String",
      "scope": "System",
      "permissionLevel": "User",
      "isSensitive": false,
      "validationRules": "String"
    },
    {
      "category": "Receiving",
      "key": "Receiving.UiText.HeatLot.FieldHeader",
      "displayName": "Heat/Lot - Field Header",
      "defaultValue": "Heat/Lot Number (Optional)",
      "dataType": "String",
      "scope": "System",
      "permissionLevel": "User",
      "isSensitive": false,
      "validationRules": "String"
    },
    {
      "category": "Receiving",
      "key": "Receiving.UiText.HeatLot.FieldPlaceholder",
      "displayName": "Heat/Lot - Field Placeholder",
      "defaultValue": "Enter heat/lot number or leave blank",
      "dataType": "String",
      "scope": "System",
      "permissionLevel": "User",
      "isSensitive": false,
      "validationRules": "String"
    },
    {
      "category": "Receiving",
      "key": "Receiving.UiText.PackageType.Header",
      "displayName": "Package Type - Header",
      "defaultValue": "Package Type (Applied to all loads)",
      "dataType": "String",
      "scope": "System",
      "permissionLevel": "User",
      "isSensitive": false,
      "validationRules": "String"
    },
    {
      "category": "Receiving",
      "key": "Receiving.UiText.PackageType.ComboHeader",
      "displayName": "Package Type - Combo Header",
      "defaultValue": "Type",
      "dataType": "String",
      "scope": "System",
      "permissionLevel": "User",
      "isSensitive": false,
      "validationRules": "String"
    },
    {
      "category": "Receiving",
      "key": "Receiving.UiText.PackageType.CustomHeader",
      "displayName": "Package Type - Custom Header",
      "defaultValue": "Custom Name",
      "dataType": "String",
      "scope": "System",
      "permissionLevel": "User",
      "isSensitive": false,
      "validationRules": "String"
    },
    {
      "category": "Receiving",
      "key": "Receiving.UiText.PackageType.SaveAsDefault",
      "displayName": "Package Type - Save as Default",
      "defaultValue": "Save as default for this part",
      "dataType": "String",
      "scope": "System",
      "permissionLevel": "User",
      "isSensitive": false,
      "validationRules": "String"
    },
    {
      "category": "Receiving",
      "key": "Receiving.UiText.PackageType.LoadNumberPrefix",
      "displayName": "Package Type - Load Number Prefix",
      "defaultValue": "#{0}",
      "dataType": "String",
      "scope": "System",
      "permissionLevel": "User",
      "isSensitive": false,
      "validationRules": "String"
    },
    {
      "category": "Receiving",
      "key": "Receiving.UiText.PackageType.PackagesPerLoad",
      "displayName": "Package Type - Packages Per Load",
      "defaultValue": "Packages per Load",
      "dataType": "String",
      "scope": "System",
      "permissionLevel": "User",
      "isSensitive": false,
      "validationRules": "String"
    },
    {
      "category": "Receiving",
      "key": "Receiving.UiText.PackageType.WeightPerPackage",
      "displayName": "Package Type - Weight Per Package",
      "defaultValue": "Weight per Package",
      "dataType": "String",
      "scope": "System",
      "permissionLevel": "User",
      "isSensitive": false,
      "validationRules": "String"
    },
    {
      "category": "Receiving",
      "key": "Receiving.UiText.Review.EntryLabel",
      "displayName": "Review - Entry Label",
      "defaultValue": "Entry",
      "dataType": "String",
      "scope": "System",
      "permissionLevel": "User",
      "isSensitive": false,
      "validationRules": "String"
    },
    {
      "category": "Receiving",
      "key": "Receiving.UiText.Review.OfLabel",
      "displayName": "Review - Of Label",
      "defaultValue": "of",
      "dataType": "String",
      "scope": "System",
      "permissionLevel": "User",
      "isSensitive": false,
      "validationRules": "String"
    },
    {
      "category": "Receiving",
      "key": "Receiving.UiText.Review.LoadNumber",
      "displayName": "Review - Load Number",
      "defaultValue": "Load Number",
      "dataType": "String",
      "scope": "System",
      "permissionLevel": "User",
      "isSensitive": false,
      "validationRules": "String"
    },
    {
      "category": "Receiving",
      "key": "Receiving.UiText.Review.PurchaseOrderNumber",
      "displayName": "Review - Purchase Order Number",
      "defaultValue": "Purchase Order Number",
      "dataType": "String",
      "scope": "System",
      "permissionLevel": "User",
      "isSensitive": false,
      "validationRules": "String"
    },
    {
      "category": "Receiving",
      "key": "Receiving.UiText.Review.PartId",
      "displayName": "Review - Part ID",
      "defaultValue": "Part ID",
      "dataType": "String",
      "scope": "System",
      "permissionLevel": "User",
      "isSensitive": false,
      "validationRules": "String"
    },
    {
      "category": "Receiving",
      "key": "Receiving.UiText.Review.RemainingQuantity",
      "displayName": "Review - Remaining Quantity",
      "defaultValue": "Remaining Quantity",
      "dataType": "String",
      "scope": "System",
      "permissionLevel": "User",
      "isSensitive": false,
      "validationRules": "String"
    },
    {
      "category": "Receiving",
      "key": "Receiving.UiText.Review.WeightQuantity",
      "displayName": "Review - Weight/Quantity",
      "defaultValue": "Weight/Quantity",
      "dataType": "String",
      "scope": "System",
      "permissionLevel": "User",
      "isSensitive": false,
      "validationRules": "String"
    },
    {
      "category": "Receiving",
      "key": "Receiving.UiText.Review.HeatLotNumber",
      "displayName": "Review - Heat/Lot Number",
      "defaultValue": "Heat/Lot Number",
      "dataType": "String",
      "scope": "System",
      "permissionLevel": "User",
      "isSensitive": false,
      "validationRules": "String"
    },
    {
      "category": "Receiving",
      "key": "Receiving.UiText.Review.PackagesPerLoad",
      "displayName": "Review - Packages Per Load",
      "defaultValue": "Packages Per Load",
      "dataType": "String",
      "scope": "System",
      "permissionLevel": "User",
      "isSensitive": false,
      "validationRules": "String"
    },
    {
      "category": "Receiving",
      "key": "Receiving.UiText.Review.PackageType",
      "displayName": "Review - Package Type",
      "defaultValue": "Package Type",
      "dataType": "String",
      "scope": "System",
      "permissionLevel": "User",
      "isSensitive": false,
      "validationRules": "String"
    },
    {
      "category": "Receiving",
      "key": "Receiving.UiText.Review.PreviousLabel",
      "displayName": "Review - Previous Label",
      "defaultValue": "Previous",
      "dataType": "String",
      "scope": "System",
      "permissionLevel": "User",
      "isSensitive": false,
      "validationRules": "String"
    },
    {
      "category": "Receiving",
      "key": "Receiving.UiText.Review.NextLabel",
      "displayName": "Review - Next Label",
      "defaultValue": "Next",
      "dataType": "String",
      "scope": "System",
      "permissionLevel": "User",
      "isSensitive": false,
      "validationRules": "String"
    },
    {
      "category": "Receiving",
      "key": "Receiving.UiText.Review.TableViewLabel",
      "displayName": "Review - Table View Label",
      "defaultValue": "Table View",
      "dataType": "String",
      "scope": "System",
      "permissionLevel": "User",
      "isSensitive": false,
      "validationRules": "String"
    },
    {
      "category": "Receiving",
      "key": "Receiving.UiText.Review.SingleViewLabel",
      "displayName": "Review - Single View Label",
      "defaultValue": "Single View",
      "dataType": "String",
      "scope": "System",
      "permissionLevel": "User",
      "isSensitive": false,
      "validationRules": "String"
    },
    {
      "category": "Receiving",
      "key": "Receiving.UiText.Review.AddAnother",
      "displayName": "Review - Add Another",
      "defaultValue": "Add Another Part/PO",
      "dataType": "String",
      "scope": "System",
      "permissionLevel": "User",
      "isSensitive": false,
      "validationRules": "String"
    },
    {
      "category": "Receiving",
      "key": "Receiving.UiText.Review.SaveToDatabase",
      "displayName": "Review - Save to Database",
      "defaultValue": "Save to Database",
      "dataType": "String",
      "scope": "System",
      "permissionLevel": "User",
      "isSensitive": false,
      "validationRules": "String"
    },
    {
      "category": "Receiving",
      "key": "Receiving.UiText.Review.Column.LoadNumber",
      "displayName": "Review - Load # Column",
      "defaultValue": "Load #",
      "dataType": "String",
      "scope": "System",
      "permissionLevel": "User",
      "isSensitive": false,
      "validationRules": "String"
    },
    {
      "category": "Receiving",
      "key": "Receiving.UiText.Review.Column.PoNumber",
      "displayName": "Review - PO Number Column",
      "defaultValue": "PO Number",
      "dataType": "String",
      "scope": "System",
      "permissionLevel": "User",
      "isSensitive": false,
      "validationRules": "String"
    },
    {
      "category": "Receiving",
      "key": "Receiving.UiText.Review.Column.PartId",
      "displayName": "Review - Part ID Column",
      "defaultValue": "Part ID",
      "dataType": "String",
      "scope": "System",
      "permissionLevel": "User",
      "isSensitive": false,
      "validationRules": "String"
    },
    {
      "category": "Receiving",
      "key": "Receiving.UiText.Review.Column.RemainingQty",
      "displayName": "Review - Remaining Qty Column",
      "defaultValue": "Remaining Qty",
      "dataType": "String",
      "scope": "System",
      "permissionLevel": "User",
      "isSensitive": false,
      "validationRules": "String"
    },
    {
      "category": "Receiving",
      "key": "Receiving.UiText.Review.Column.WeightQty",
      "displayName": "Review - Weight/Qty Column",
      "defaultValue": "Weight/Qty",
      "dataType": "String",
      "scope": "System",
      "permissionLevel": "User",
      "isSensitive": false,
      "validationRules": "String"
    },
    {
      "category": "Receiving",
      "key": "Receiving.UiText.Review.Column.HeatLot",
      "displayName": "Review - Heat/Lot Column",
      "defaultValue": "Heat/Lot #",
      "dataType": "String",
      "scope": "System",
      "permissionLevel": "User",
      "isSensitive": false,
      "validationRules": "String"
    },
    {
      "category": "Receiving",
      "key": "Receiving.UiText.Review.Column.Pkgs",
      "displayName": "Review - Pkgs Column",
      "defaultValue": "Pkgs",
      "dataType": "String",
      "scope": "System",
      "permissionLevel": "User",
      "isSensitive": false,
      "validationRules": "String"
    },
    {
      "category": "Receiving",
      "key": "Receiving.UiText.Review.Column.PkgType",
      "displayName": "Review - Pkg Type Column",
      "defaultValue": "Pkg Type",
      "dataType": "String",
      "scope": "System",
      "permissionLevel": "User",
      "isSensitive": false,
      "validationRules": "String"
    },
    {
      "category": "Receiving",
      "key": "Receiving.Workflow.StepTitle.ModeSelection",
      "displayName": "Workflow - Mode Selection Step",
      "defaultValue": "Receiving - Mode Selection",
      "dataType": "String",
      "scope": "System",
      "permissionLevel": "User",
      "isSensitive": false,
      "validationRules": "String"
    },
    {
      "category": "Receiving",
      "key": "Receiving.Workflow.StepTitle.ManualEntry",
      "displayName": "Workflow - Manual Entry Step",
      "defaultValue": "Receiving - Manual Entry",
      "dataType": "String",
      "scope": "System",
      "permissionLevel": "User",
      "isSensitive": false,
      "validationRules": "String"
    },
    {
      "category": "Receiving",
      "key": "Receiving.Workflow.StepTitle.EditMode",
      "displayName": "Workflow - Edit Mode Step",
      "defaultValue": "Receiving - Edit Mode",
      "dataType": "String",
      "scope": "System",
      "permissionLevel": "User",
      "isSensitive": false,
      "validationRules": "String"
    },
    {
      "category": "Receiving",
      "key": "Receiving.Workflow.StepTitle.PoEntry",
      "displayName": "Workflow - PO Entry Step",
      "defaultValue": "Receiving - Enter PO Number",
      "dataType": "String",
      "scope": "System",
      "permissionLevel": "User",
      "isSensitive": false,
      "validationRules": "String"
    },
    {
      "category": "Receiving",
      "key": "Receiving.Workflow.StepTitle.PartSelection",
      "displayName": "Workflow - Part Selection Step",
      "defaultValue": "Receiving - Select Part",
      "dataType": "String",
      "scope": "System",
      "permissionLevel": "User",
      "isSensitive": false,
      "validationRules": "String"
    },
    {
      "category": "Receiving",
      "key": "Receiving.Workflow.StepTitle.LoadEntry",
      "displayName": "Workflow - Load Entry Step",
      "defaultValue": "Receiving - Enter Number of Loads",
      "dataType": "String",
      "scope": "System",
      "permissionLevel": "User",
      "isSensitive": false,
      "validationRules": "String"
    },
    {
      "category": "Receiving",
      "key": "Receiving.Workflow.StepTitle.WeightQuantity",
      "displayName": "Workflow - Weight/Quantity Step",
      "defaultValue": "Receiving - Enter Weight/Quantity",
      "dataType": "String",
      "scope": "System",
      "permissionLevel": "User",
      "isSensitive": false,
      "validationRules": "String"
    },
    {
      "category": "Receiving",
      "key": "Receiving.Workflow.StepTitle.HeatLot",
      "displayName": "Workflow - Heat/Lot Step",
      "defaultValue": "Receiving - Enter Heat/Lot Numbers",
      "dataType": "String",
      "scope": "System",
      "permissionLevel": "User",
      "isSensitive": false,
      "validationRules": "String"
    },
    {
      "category": "Receiving",
      "key": "Receiving.Workflow.StepTitle.PackageType",
      "displayName": "Workflow - Package Type Step",
      "defaultValue": "Receiving - Select Package Type",
      "dataType": "String",
      "scope": "System",
      "permissionLevel": "User",
      "isSensitive": false,
      "validationRules": "String"
    },
    {
      "category": "Receiving",
      "key": "Receiving.Workflow.StepTitle.ReviewAndSave",
      "displayName": "Workflow - Review & Save Step",
      "defaultValue": "Receiving - Review & Save",
      "dataType": "String",
      "scope": "System",
      "permissionLevel": "User",
      "isSensitive": false,
      "validationRules": "String"
    },
    {
      "category": "Receiving",
      "key": "Receiving.Defaults.DefaultReceivingMode",
      "displayName": "Default Receiving Mode",
      "defaultValue": "Guided",
      "dataType": "String",
      "scope": "User",
      "permissionLevel": "User",
      "isSensitive": false,
      "validationRules": "Allowed: Guided, Manual, Edit"
    },
    {
      "category": "Receiving",
      "key": "Receiving.Defaults.CsvSaveLocation",
      "displayName": "CSV File Save Location",
      "defaultValue": "",
      "dataType": "String",
      "scope": "User",
      "permissionLevel": "User",
      "isSensitive": false,
      "validationRules": "Path"
    },
    {
      "category": "Receiving",
      "key": "Receiving.Workflow.StepTitle.Saving",
      "displayName": "Workflow - Saving Step",
      "defaultValue": "Receiving - Saving...",
      "dataType": "String",
      "scope": "System",
      "permissionLevel": "User",
      "isSensitive": false,
      "validationRules": "String"
    },
    {
      "category": "Receiving",
      "key": "Receiving.Workflow.StepTitle.Complete",
      "displayName": "Workflow - Complete Step",
      "defaultValue": "Receiving - Complete",
      "dataType": "String",
      "scope": "System",
      "permissionLevel": "User",
      "isSensitive": false,
      "validationRules": "String"
    },
    {
      "category": "Receiving",
      "key": "Receiving.Workflow.SaveProgress.Initializing",
      "displayName": "Workflow - Initializing",
      "defaultValue": "Initializing...",
      "dataType": "String",
      "scope": "System",
      "permissionLevel": "User",
      "isSensitive": false,
      "validationRules": "String"
    },
    {
      "category": "Receiving",
      "key": "Receiving.Workflow.SaveProgress.SavingCsv",
      "displayName": "Workflow - Saving CSV",
      "defaultValue": "Saving to local and network CSV...",
      "dataType": "String",
      "scope": "System",
      "permissionLevel": "User",
      "isSensitive": false,
      "validationRules": "String"
    },
    {
      "category": "Receiving",
      "key": "Receiving.Workflow.Dialog.ResetCsv.Title",
      "displayName": "Workflow - Reset CSV Dialog Title",
      "defaultValue": "Reset CSV Files",
      "dataType": "String",
      "scope": "System",
      "permissionLevel": "User",
      "isSensitive": false,
      "validationRules": "String"
    },
    {
      "category": "Receiving",
      "key": "Receiving.Workflow.Dialog.ResetCsv.Content",
      "displayName": "Workflow - Reset CSV Dialog Content",
      "defaultValue": "Are you sure you want to delete the local and network CSV files? This action cannot be undone.",
      "dataType": "String",
      "scope": "System",
      "permissionLevel": "User",
      "isSensitive": false,
      "validationRules": "String"
    },
    {
      "category": "Receiving",
      "key": "Receiving.Workflow.Dialog.ResetCsv.Delete",
      "displayName": "Workflow - Reset CSV Dialog Delete",
      "defaultValue": "Delete",
      "dataType": "String",
      "scope": "System",
      "permissionLevel": "User",
      "isSensitive": false,
      "validationRules": "String"
    },
    {
      "category": "Receiving",
      "key": "Receiving.Workflow.Dialog.ResetCsv.Cancel",
      "displayName": "Workflow - Reset CSV Dialog Cancel",
      "defaultValue": "Cancel",
      "dataType": "String",
      "scope": "System",
      "permissionLevel": "User",
      "isSensitive": false,
      "validationRules": "String"
    },
    {
      "category": "Receiving",
      "key": "Receiving.Workflow.Dialog.DbSaveFailed.Title",
      "displayName": "Workflow - DB Save Failed Dialog Title",
      "defaultValue": "Database Save Failed",
      "dataType": "String",
      "scope": "System",
      "permissionLevel": "User",
      "isSensitive": false,
      "validationRules": "String"
    },
    {
      "category": "Receiving",
      "key": "Receiving.Workflow.Dialog.DbSaveFailed.DeleteAnyway",
      "displayName": "Workflow - DB Save Failed Delete Anyway",
      "defaultValue": "Delete Anyway",
      "dataType": "String",
      "scope": "System",
      "permissionLevel": "User",
      "isSensitive": false,
      "validationRules": "String"
    },
    {
      "category": "Receiving",
      "key": "Receiving.Workflow.Dialog.DbSaveFailed.Cancel",
      "displayName": "Workflow - DB Save Failed Cancel",
      "defaultValue": "Cancel",
      "dataType": "String",
      "scope": "System",
      "permissionLevel": "User",
      "isSensitive": false,
      "validationRules": "String"
    },
    {
      "category": "Receiving",
      "key": "Receiving.Workflow.Status.CsvDeletedSuccess",
      "displayName": "Workflow - CSV Deleted Success",
      "defaultValue": "CSV files deleted successfully.",
      "dataType": "String",
      "scope": "System",
      "permissionLevel": "User",
      "isSensitive": false,
      "validationRules": "String"
    },
    {
      "category": "Receiving",
      "key": "Receiving.Workflow.Status.CsvDeletedFailed",
      "displayName": "Workflow - CSV Deleted Failed",
      "defaultValue": "Failed to delete CSV files or files not found.",
      "dataType": "String",
      "scope": "System",
      "permissionLevel": "User",
      "isSensitive": false,
      "validationRules": "String"
    },
    {
      "category": "Receiving",
      "key": "Receiving.Workflow.Status.WorkflowCleared",
      "displayName": "Workflow - Workflow Cleared",
      "defaultValue": "Workflow cleared. Please select a mode.",
      "dataType": "String",
      "scope": "System",
      "permissionLevel": "User",
      "isSensitive": false,
      "validationRules": "String"
    },
    {
      "category": "Receiving",
      "key": "Receiving.Dialogs.ConfirmModeSelection.Title",
      "displayName": "Dialogs - Confirm Mode Selection Title",
      "defaultValue": "Confirm Mode Selection",
      "dataType": "String",
      "scope": "System",
      "permissionLevel": "User",
      "isSensitive": false,
      "validationRules": "String"
    },
    {
      "category": "Receiving",
      "key": "Receiving.Dialogs.ConfirmModeSelection.Content",
      "displayName": "Dialogs - Confirm Mode Selection Content",
      "defaultValue": "Selecting a new mode will reset all unsaved data in the current workflow. Do you want to continue?",
      "dataType": "String",
      "scope": "System",
      "permissionLevel": "User",
      "isSensitive": false,
      "validationRules": "String"
    },
    {
      "category": "Receiving",
      "key": "Receiving.Dialogs.ConfirmModeSelection.Continue",
      "displayName": "Dialogs - Confirm Mode Selection Continue",
      "defaultValue": "Continue",
      "dataType": "String",
      "scope": "System",
      "permissionLevel": "User",
      "isSensitive": false,
      "validationRules": "String"
    },
    {
      "category": "Receiving",
      "key": "Receiving.Dialogs.ConfirmModeSelection.Cancel",
      "displayName": "Dialogs - Confirm Mode Selection Cancel",
      "defaultValue": "Cancel",
      "dataType": "String",
      "scope": "System",
      "permissionLevel": "User",
      "isSensitive": false,
      "validationRules": "String"
    },
    {
      "category": "Receiving",
      "key": "Receiving.Dialogs.ConfirmChangeMode.Title",
      "displayName": "Dialogs - Confirm Change Mode Title",
      "defaultValue": "Change Mode?",
      "dataType": "String",
      "scope": "System",
      "permissionLevel": "User",
      "isSensitive": false,
      "validationRules": "String"
    },
    {
      "category": "Receiving",
      "key": "Receiving.Dialogs.ConfirmChangeMode.Content",
      "displayName": "Dialogs - Confirm Change Mode Content",
      "defaultValue": "Returning to mode selection will clear all current work in progress. This cannot be undone. Are you sure?",
      "dataType": "String",
      "scope": "System",
      "permissionLevel": "User",
      "isSensitive": false,
      "validationRules": "String"
    },
    {
      "category": "Receiving",
      "key": "Receiving.Dialogs.ConfirmChangeMode.Confirm",
      "displayName": "Dialogs - Confirm Change Mode Confirm",
      "defaultValue": "Yes, Change Mode",
      "dataType": "String",
      "scope": "System",
      "permissionLevel": "User",
      "isSensitive": false,
      "validationRules": "String"
    },
    {
      "category": "Receiving",
      "key": "Receiving.Dialogs.ConfirmChangeMode.Cancel",
      "displayName": "Dialogs - Confirm Change Mode Cancel",
      "defaultValue": "Cancel",
      "dataType": "String",
      "scope": "System",
      "permissionLevel": "User",
      "isSensitive": false,
      "validationRules": "String"
    },
    {
      "category": "Receiving",
      "key": "Receiving.Dialogs.ManualEntry.AddMultiple.Title",
      "displayName": "Dialogs - Manual Entry Add Multiple Title",
      "defaultValue": "Add Multiple Rows",
      "dataType": "String",
      "scope": "System",
      "permissionLevel": "User",
      "isSensitive": false,
      "validationRules": "String"
    },
    {
      "category": "Receiving",
      "key": "Receiving.Dialogs.ManualEntry.AddMultiple.Add",
      "displayName": "Dialogs - Manual Entry Add Multiple Add",
      "defaultValue": "Add",
      "dataType": "String",
      "scope": "System",
      "permissionLevel": "User",
      "isSensitive": false,
      "validationRules": "String"
    },
    {
      "category": "Receiving",
      "key": "Receiving.Dialogs.ManualEntry.AddMultiple.Cancel",
      "displayName": "Dialogs - Manual Entry Add Multiple Cancel",
      "defaultValue": "Cancel",
      "dataType": "String",
      "scope": "System",
      "permissionLevel": "User",
      "isSensitive": false,
      "validationRules": "String"
    },
    {
      "category": "Receiving",
      "key": "Receiving.Dialogs.Review.AddAnother.Title",
      "displayName": "Dialogs - Review Add Another Title",
      "defaultValue": "Add Another Part/PO",
      "dataType": "String",
      "scope": "System",
      "permissionLevel": "User",
      "isSensitive": false,
      "validationRules": "String"
    },
    {
      "category": "Receiving",
      "key": "Receiving.Dialogs.Review.AddAnother.Content",
      "displayName": "Dialogs - Review Add Another Content",
      "defaultValue": "Current form data will be cleared to start a new entry. Your reviewed loads are preserved. Continue?",
      "dataType": "String",
      "scope": "System",
      "permissionLevel": "User",
      "isSensitive": false,
      "validationRules": "String"
    },
    {
      "category": "Receiving",
      "key": "Receiving.Dialogs.Review.AddAnother.Continue",
      "displayName": "Dialogs - Review Add Another Continue",
      "defaultValue": "Continue",
      "dataType": "String",
      "scope": "System",
      "permissionLevel": "User",
      "isSensitive": false,
      "validationRules": "String"
    },
    {
      "category": "Receiving",
      "key": "Receiving.Dialogs.Review.AddAnother.Cancel",
      "displayName": "Dialogs - Review Add Another Cancel",
      "defaultValue": "Cancel",
      "dataType": "String",
      "scope": "System",
      "permissionLevel": "User",
      "isSensitive": false,
      "validationRules": "String"
    },
    {
      "category": "Receiving",
      "key": "Receiving.Messages.Error.UnableToDisplayDialog",
      "displayName": "Messages - Unable to Display Dialog",
      "defaultValue": "Unable to display dialog",
      "dataType": "String",
      "scope": "System",
      "permissionLevel": "User",
      "isSensitive": false,
      "validationRules": "String"
    },
    {
      "category": "Receiving",
      "key": "Receiving.Messages.Error.PoRequired",
      "displayName": "Messages - PO Required",
      "defaultValue": "Please enter a PO number.",
      "dataType": "String",
      "scope": "System",
      "permissionLevel": "User",
      "isSensitive": false,
      "validationRules": "String"
    },
    {
      "category": "Receiving",
      "key": "Receiving.Messages.Error.PartIdRequired",
      "displayName": "Messages - Part ID Required",
      "defaultValue": "Please enter a Part ID.",
      "dataType": "String",
      "scope": "System",
      "permissionLevel": "User",
      "isSensitive": false,
      "validationRules": "String"
    },
    {
      "category": "Receiving",
      "key": "Receiving.Messages.Error.PoNotFound",
      "displayName": "Messages - PO Not Found",
      "defaultValue": "PO not found or contains no parts.",
      "dataType": "String",
      "scope": "System",
      "permissionLevel": "User",
      "isSensitive": false,
      "validationRules": "String"
    },
    {
      "category": "Receiving",
      "key": "Receiving.Messages.Error.PartNotFound",
      "displayName": "Messages - Part Not Found",
      "defaultValue": "Part not found.",
      "dataType": "String",
      "scope": "System",
      "permissionLevel": "User",
      "isSensitive": false,
      "validationRules": "String"
    },
    {
      "category": "Receiving",
      "key": "Receiving.Messages.Info.PoLoadedWithParts",
      "displayName": "Messages - PO Loaded With Parts",
      "defaultValue": "Purchase Order {0} loaded with {1} parts.",
      "dataType": "String",
      "scope": "System",
      "permissionLevel": "User",
      "isSensitive": false,
      "validationRules": "String"
    },
    {
      "category": "Receiving",
      "key": "Receiving.Messages.Info.PartFound",
      "displayName": "Messages - Part Found",
      "defaultValue": "Part {0} found.",
      "dataType": "String",
      "scope": "System",
      "permissionLevel": "User",
      "isSensitive": false,
      "validationRules": "String"
    },
    {
      "category": "Receiving",
      "key": "Receiving.Messages.Warning.SameDayReceiving",
      "displayName": "Messages - Same Day Receiving Warning",
      "defaultValue": "Warning: {0:N2} of this part has already been received today on this PO.",
      "dataType": "String",
      "scope": "System",
      "permissionLevel": "User",
      "isSensitive": false,
      "validationRules": "String"
    },
    {
      "category": "Receiving",
      "key": "Receiving.Messages.Warning.ExceedsOrdered",
      "displayName": "Messages - Exceeds Ordered Warning",
      "defaultValue": "Warning: Total quantity ({0:N2}) exceeds PO ordered amount ({1:N2}).",
      "dataType": "String",
      "scope": "System",
      "permissionLevel": "User",
      "isSensitive": false,
      "validationRules": "String"
    },
    {
      "category": "Receiving",
      "key": "Receiving.Messages.Info.NonPoItem",
      "displayName": "Messages - Non-PO Item",
      "defaultValue": "Non-PO Item",
      "dataType": "String",
      "scope": "System",
      "permissionLevel": "User",
      "isSensitive": false,
      "validationRules": "String"
    },
    {
      "category": "Receiving",
      "key": "Receiving.Accessibility.ModeSelection.GuidedButton",
      "displayName": "Accessibility - Mode Selection Guided",
      "defaultValue": "Guided Wizard Mode",
      "dataType": "String",
      "scope": "System",
      "permissionLevel": "User",
      "isSensitive": false,
      "validationRules": "String"
    },
    {
      "category": "Receiving",
      "key": "Receiving.Accessibility.ModeSelection.ManualButton",
      "displayName": "Accessibility - Mode Selection Manual",
      "defaultValue": "Manual Entry Mode",
      "dataType": "String",
      "scope": "System",
      "permissionLevel": "User",
      "isSensitive": false,
      "validationRules": "String"
    },
    {
      "category": "Receiving",
      "key": "Receiving.Accessibility.ModeSelection.EditButton",
      "displayName": "Accessibility - Mode Selection Edit",
      "defaultValue": "Edit Mode",
      "dataType": "String",
      "scope": "System",
      "permissionLevel": "User",
      "isSensitive": false,
      "validationRules": "String"
    },
    {
      "category": "Receiving",
      "key": "Receiving.Accessibility.PoEntry.PONumber",
      "displayName": "Accessibility - PO Entry PO Number",
      "defaultValue": "Purchase Order Number",
      "dataType": "String",
      "scope": "System",
      "permissionLevel": "User",
      "isSensitive": false,
      "validationRules": "String"
    },
    {
      "category": "Receiving",
      "key": "Receiving.Accessibility.PoEntry.LoadPo",
      "displayName": "Accessibility - PO Entry Load PO",
      "defaultValue": "Load Purchase Order",
      "dataType": "String",
      "scope": "System",
      "permissionLevel": "User",
      "isSensitive": false,
      "validationRules": "String"
    },
    {
      "category": "Receiving",
      "key": "Receiving.Accessibility.PoEntry.PartId",
      "displayName": "Accessibility - PO Entry Part ID",
      "defaultValue": "Part Identifier",
      "dataType": "String",
      "scope": "System",
      "permissionLevel": "User",
      "isSensitive": false,
      "validationRules": "String"
    },
    {
      "category": "Receiving",
      "key": "Receiving.Accessibility.PoEntry.LookupPart",
      "displayName": "Accessibility - PO Entry Lookup Part",
      "defaultValue": "Look Up Part",
      "dataType": "String",
      "scope": "System",
      "permissionLevel": "User",
      "isSensitive": false,
      "validationRules": "String"
    },
    {
      "category": "Receiving",
      "key": "Receiving.Accessibility.PoEntry.PartsList",
      "displayName": "Accessibility - PO Entry Parts List",
      "defaultValue": "Parts List",
      "dataType": "String",
      "scope": "System",
      "permissionLevel": "User",
      "isSensitive": false,
      "validationRules": "String"
    },
    {
      "category": "Receiving",
      "key": "Receiving.Accessibility.LoadEntry.NumberOfLoads",
      "displayName": "Accessibility - Load Entry Number of Loads",
      "defaultValue": "Number of Loads",
      "dataType": "String",
      "scope": "System",
      "permissionLevel": "User",
      "isSensitive": false,
      "validationRules": "String"
    },
    {
      "category": "Receiving",
      "key": "Receiving.Accessibility.WeightQuantity.Input",
      "displayName": "Accessibility - Weight/Quantity Input",
      "defaultValue": "Weight Quantity",
      "dataType": "String",
      "scope": "System",
      "permissionLevel": "User",
      "isSensitive": false,
      "validationRules": "String"
    },
    {
      "category": "Receiving",
      "key": "Receiving.Accessibility.HeatLot.Number",
      "displayName": "Accessibility - Heat/Lot Number",
      "defaultValue": "Heat Lot Number",
      "dataType": "String",
      "scope": "System",
      "permissionLevel": "User",
      "isSensitive": false,
      "validationRules": "String"
    },
    {
      "category": "Receiving",
      "key": "Receiving.Accessibility.PackageType.Combo",
      "displayName": "Accessibility - Package Type Combo",
      "defaultValue": "Package Type",
      "dataType": "String",
      "scope": "System",
      "permissionLevel": "User",
      "isSensitive": false,
      "validationRules": "String"
    },
    {
      "category": "Receiving",
      "key": "Receiving.Accessibility.PackageType.CustomName",
      "displayName": "Accessibility - Package Type Custom Name",
      "defaultValue": "Custom Package Name",
      "dataType": "String",
      "scope": "System",
      "permissionLevel": "User",
      "isSensitive": false,
      "validationRules": "String"
    },
    {
      "category": "Receiving",
      "key": "Receiving.Accessibility.PackageType.PackagesPerLoad",
      "displayName": "Accessibility - Package Type Packages Per Load",
      "defaultValue": "Packages per Load",
      "dataType": "String",
      "scope": "System",
      "permissionLevel": "User",
      "isSensitive": false,
      "validationRules": "String"
    },
    {
      "category": "Receiving",
      "key": "Receiving.Accessibility.Review.PreviousEntry",
      "displayName": "Accessibility - Review Previous Entry",
      "defaultValue": "Previous Entry",
      "dataType": "String",
      "scope": "System",
      "permissionLevel": "User",
      "isSensitive": false,
      "validationRules": "String"
    },
    {
      "category": "Receiving",
      "key": "Receiving.Accessibility.Review.NextEntry",
      "displayName": "Accessibility - Review Next Entry",
      "defaultValue": "Next Entry",
      "dataType": "String",
      "scope": "System",
      "permissionLevel": "User",
      "isSensitive": false,
      "validationRules": "String"
    },
    {
      "category": "Receiving",
      "key": "Receiving.Accessibility.Review.SwitchToTable",
      "displayName": "Accessibility - Review Switch to Table",
      "defaultValue": "Switch to Table View",
      "dataType": "String",
      "scope": "System",
      "permissionLevel": "User",
      "isSensitive": false,
      "validationRules": "String"
    },
    {
      "category": "Receiving",
      "key": "Receiving.Accessibility.Review.SwitchToSingle",
      "displayName": "Accessibility - Review Switch to Single",
      "defaultValue": "Switch to Single View",
      "dataType": "String",
      "scope": "System",
      "permissionLevel": "User",
      "isSensitive": false,
      "validationRules": "String"
    },
    {
      "category": "Receiving",
      "key": "Receiving.Accessibility.Review.EntriesTable",
      "displayName": "Accessibility - Review Entries Table",
      "defaultValue": "Receiving Entries Table",
      "dataType": "String",
      "scope": "System",
      "permissionLevel": "User",
      "isSensitive": false,
      "validationRules": "String"
    },
    {
      "category": "Receiving",
      "key": "Receiving.Accessibility.Review.AddAnother",
      "displayName": "Accessibility - Review Add Another",
      "defaultValue": "Add Another Part or PO",
      "dataType": "String",
      "scope": "System",
      "permissionLevel": "User",
      "isSensitive": false,
      "validationRules": "String"
    },
    {
      "category": "Receiving",
      "key": "Receiving.Accessibility.Review.SaveToDatabase",
      "displayName": "Accessibility - Review Save to Database",
      "defaultValue": "Save to Database",
      "dataType": "String",
      "scope": "System",
      "permissionLevel": "User",
      "isSensitive": false,
      "validationRules": "String"
    },
    {
      "category": "Receiving",
      "key": "Receiving.Validation.RequirePoNumber",
      "displayName": "Validation - Require PO Number",
      "defaultValue": "false",
      "dataType": "Bool",
      "scope": "System",
      "permissionLevel": "User",
      "isSensitive": false,
      "validationRules": "Bool"
    },
    {
      "category": "Receiving",
      "key": "Receiving.Validation.RequirePartId",
      "displayName": "Validation - Require Part ID",
      "defaultValue": "true",
      "dataType": "Bool",
      "scope": "System",
      "permissionLevel": "User",
      "isSensitive": false,
      "validationRules": "Bool"
    },
    {
      "category": "Receiving",
      "key": "Receiving.Validation.RequireQuantity",
      "displayName": "Validation - Require Quantity",
      "defaultValue": "true",
      "dataType": "Bool",
      "scope": "System",
      "permissionLevel": "User",
      "isSensitive": false,
      "validationRules": "Bool"
    },
    {
      "category": "Receiving",
      "key": "Receiving.Validation.RequireHeatLot",
      "displayName": "Validation - Require Heat/Lot",
      "defaultValue": "false",
      "dataType": "Bool",
      "scope": "System",
      "permissionLevel": "User",
      "isSensitive": false,
      "validationRules": "Bool"
    },
    {
      "category": "Receiving",
      "key": "Receiving.Validation.AllowNegativeQuantity",
      "displayName": "Validation - Allow Negative Quantity",
      "defaultValue": "false",
      "dataType": "Bool",
      "scope": "System",
      "permissionLevel": "User",
      "isSensitive": false,
      "validationRules": "Bool"
    },
    {
      "category": "Receiving",
      "key": "Receiving.Validation.ValidatePoExists",
      "displayName": "Validation - Validate PO Exists",
      "defaultValue": "true",
      "dataType": "Bool",
      "scope": "System",
      "permissionLevel": "User",
      "isSensitive": false,
      "validationRules": "Bool"
    },
    {
      "category": "Receiving",
      "key": "Receiving.Validation.ValidatePartExists",
      "displayName": "Validation - Validate Part Exists",
      "defaultValue": "true",
      "dataType": "Bool",
      "scope": "System",
      "permissionLevel": "User",
      "isSensitive": false,
      "validationRules": "Bool"
    },
    {
      "category": "Receiving",
      "key": "Receiving.Validation.WarnOnQuantityExceedsPo",
      "displayName": "Validation - Warn on Quantity Exceeds PO",
      "defaultValue": "true",
      "dataType": "Bool",
      "scope": "System",
      "permissionLevel": "User",
      "isSensitive": false,
      "validationRules": "Bool"
    },
    {
      "category": "Receiving",
      "key": "Receiving.Validation.WarnOnSameDayReceiving",
      "displayName": "Validation - Warn on Same Day Receiving",
      "defaultValue": "true",
      "dataType": "Bool",
      "scope": "System",
      "permissionLevel": "User",
      "isSensitive": false,
      "validationRules": "Bool"
    },
    {
      "category": "Receiving",
      "key": "Receiving.Validation.MinLoadCount",
      "displayName": "Validation - Minimum Load Count",
      "defaultValue": "1",
      "dataType": "Int",
      "scope": "System",
      "permissionLevel": "User",
      "isSensitive": false,
      "validationRules": "Int"
    },
    {
      "category": "Receiving",
      "key": "Receiving.Validation.MaxLoadCount",
      "displayName": "Validation - Maximum Load Count",
      "defaultValue": "99",
      "dataType": "Int",
      "scope": "System",
      "permissionLevel": "User",
      "isSensitive": false,
      "validationRules": "Int"
    },
    {
      "category": "Receiving",
      "key": "Receiving.Validation.MinQuantity",
      "displayName": "Validation - Minimum Quantity",
      "defaultValue": "0",
      "dataType": "Int",
      "scope": "System",
      "permissionLevel": "User",
      "isSensitive": false,
      "validationRules": "Int"
    },
    {
      "category": "Receiving",
      "key": "Receiving.Validation.MaxQuantity",
      "displayName": "Validation - Maximum Quantity",
      "defaultValue": "999999",
      "dataType": "Int",
      "scope": "System",
      "permissionLevel": "User",
      "isSensitive": false,
      "validationRules": "Int"
    },
    {
      "category": "Receiving",
      "key": "Receiving.BusinessRules.AutoSaveEnabled",
      "displayName": "Business Rules - Auto Save Enabled",
      "defaultValue": "false",
      "dataType": "Bool",
      "scope": "System",
      "permissionLevel": "User",
      "isSensitive": false,
      "validationRules": "Bool"
    },
    {
      "category": "Receiving",
      "key": "Receiving.BusinessRules.AutoSaveIntervalSeconds",
      "displayName": "Business Rules - Auto Save Interval",
      "defaultValue": "300",
      "dataType": "Int",
      "scope": "System",
      "permissionLevel": "User",
      "isSensitive": false,
      "validationRules": "Int"
    },
    {
      "category": "Receiving",
      "key": "Receiving.BusinessRules.SaveToCsvEnabled",
      "displayName": "Business Rules - Save to CSV Enabled",
      "defaultValue": "true",
      "dataType": "Bool",
      "scope": "System",
      "permissionLevel": "User",
      "isSensitive": false,
      "validationRules": "Bool"
    },
    {
      "category": "Receiving",
      "key": "Receiving.BusinessRules.SaveToNetworkCsvEnabled",
      "displayName": "Business Rules - Save to Network CSV Enabled",
      "defaultValue": "true",
      "dataType": "Bool",
      "scope": "System",
      "permissionLevel": "User",
      "isSensitive": false,
      "validationRules": "Bool"
    },
    {
      "category": "Receiving",
      "key": "Receiving.BusinessRules.SaveToDatabaseEnabled",
      "displayName": "Business Rules - Save to Database Enabled",
      "defaultValue": "true",
      "dataType": "Bool",
      "scope": "System",
      "permissionLevel": "User",
      "isSensitive": false,
      "validationRules": "Bool"
    },
    {
      "category": "Receiving",
      "key": "Receiving.BusinessRules.DefaultModeOnStartup",
      "displayName": "Business Rules - Default Mode on Startup",
      "defaultValue": "ModeSelection",
      "dataType": "String",
      "scope": "System",
      "permissionLevel": "User",
      "isSensitive": false,
      "validationRules": "String"
    },
    {
      "category": "Receiving",
      "key": "Receiving.BusinessRules.RememberLastMode",
      "displayName": "Business Rules - Remember Last Mode",
      "defaultValue": "true",
      "dataType": "Bool",
      "scope": "User",
      "permissionLevel": "User",
      "isSensitive": false,
      "validationRules": "Bool"
    },
    {
      "category": "Receiving",
      "key": "Receiving.BusinessRules.ConfirmModeChange",
      "displayName": "Business Rules - Confirm Mode Change",
      "defaultValue": "true",
      "dataType": "Bool",
      "scope": "User",
      "permissionLevel": "User",
      "isSensitive": false,
      "validationRules": "Bool"
    },
    {
      "category": "Receiving",
      "key": "Receiving.BusinessRules.AutoFillHeatLotEnabled",
      "displayName": "Business Rules - Auto-Fill Heat/Lot Enabled",
      "defaultValue": "true",
      "dataType": "Bool",
      "scope": "System",
      "permissionLevel": "User",
      "isSensitive": false,
      "validationRules": "Bool"
    },
    {
      "category": "Receiving",
      "key": "Receiving.BusinessRules.SavePackageTypeAsDefault",
      "displayName": "Business Rules - Save Package Type as Default",
      "defaultValue": "false",
      "dataType": "Bool",
      "scope": "User",
      "permissionLevel": "User",
      "isSensitive": false,
      "validationRules": "Bool"
    },
    {
      "category": "Receiving",
      "key": "Receiving.BusinessRules.ShowReviewTableByDefault",
      "displayName": "Business Rules - Show Review Table by Default",
      "defaultValue": "false",
      "dataType": "Bool",
      "scope": "User",
      "permissionLevel": "User",
      "isSensitive": false,
      "validationRules": "Bool"
    },
    {
      "category": "Receiving",
      "key": "Receiving.BusinessRules.AllowEditAfterSave",
      "displayName": "Business Rules - Allow Edit After Save",
      "defaultValue": "true",
      "dataType": "Bool",
      "scope": "System",
      "permissionLevel": "User",
      "isSensitive": false,
      "validationRules": "Bool"
    },
    {
      "category": "Receiving",
      "key": "Receiving.Defaults.DefaultPackageType",
      "displayName": "Defaults - Default Package Type",
      "defaultValue": "Pallet",
      "dataType": "String",
      "scope": "System",
      "permissionLevel": "User",
      "isSensitive": false,
      "validationRules": "String"
    },
    {
      "category": "Receiving",
      "key": "Receiving.Defaults.DefaultPackagesPerLoad",
      "displayName": "Defaults - Default Packages Per Load",
      "defaultValue": "1",
      "dataType": "String",
      "scope": "System",
      "permissionLevel": "User",
      "isSensitive": false,
      "validationRules": "String"
    },
    {
      "category": "Receiving",
      "key": "Receiving.Defaults.DefaultWeightPerPackage",
      "displayName": "Defaults - Default Weight Per Package",
      "defaultValue": "0",
      "dataType": "String",
      "scope": "System",
      "permissionLevel": "User",
      "isSensitive": false,
      "validationRules": "String"
    },
    {
      "category": "Receiving",
      "key": "Receiving.Defaults.DefaultUnitOfMeasure",
      "displayName": "Defaults - Default Unit of Measure",
      "defaultValue": "LBS",
      "dataType": "String",
      "scope": "System",
      "permissionLevel": "User",
      "isSensitive": false,
      "validationRules": "String"
    },
    {
      "category": "Receiving",
      "key": "Receiving.Defaults.DefaultLocation",
      "displayName": "Defaults - Default Location",
      "defaultValue": "RECEIVING",
      "dataType": "String",
      "scope": "System",
      "permissionLevel": "User",
      "isSensitive": false,
      "validationRules": "String"
    },
    {
      "category": "Receiving",
      "key": "Receiving.Defaults.DefaultLoadNumberPrefix",
      "displayName": "Defaults - Default Load Number Prefix",
      "defaultValue": "L",
      "dataType": "String",
      "scope": "System",
      "permissionLevel": "User",
      "isSensitive": false,
      "validationRules": "String"
    },
    {
      "category": "Receiving",
      "key": "Receiving.Defaults.DefaultReceivingMode",
      "displayName": "Defaults - Default Receiving Mode",
      "defaultValue": "Guided",
      "dataType": "String",
      "scope": "System",
      "permissionLevel": "User",
      "isSensitive": false,
      "validationRules": "String"
    },
    {
      "category": "Receiving",
      "key": "Receiving.Integrations.ErpSyncEnabled",
      "displayName": "Integrations - ERP Sync Enabled",
      "defaultValue": "true",
      "dataType": "Bool",
      "scope": "System",
      "permissionLevel": "User",
      "isSensitive": false,
      "validationRules": "Bool"
    },
    {
      "category": "Receiving",
      "key": "Receiving.Integrations.AutoPullPoDataEnabled",
      "displayName": "Integrations - Auto Pull PO Data Enabled",
      "defaultValue": "true",
      "dataType": "Bool",
      "scope": "System",
      "permissionLevel": "User",
      "isSensitive": false,
      "validationRules": "Bool"
    },
    {
      "category": "Receiving",
      "key": "Receiving.Integrations.AutoPullPartDataEnabled",
      "displayName": "Integrations - Auto Pull Part Data Enabled",
      "defaultValue": "true",
      "dataType": "Bool",
      "scope": "System",
      "permissionLevel": "User",
      "isSensitive": false,
      "validationRules": "Bool"
    },
    {
      "category": "Receiving",
      "key": "Receiving.Integrations.SyncToInforVisual",
      "displayName": "Integrations - Sync to Infor Visual",
      "defaultValue": "false",
      "dataType": "Bool",
      "scope": "System",
      "permissionLevel": "User",
      "isSensitive": false,
      "validationRules": "Bool"
    },
    {
      "category": "Receiving",
      "key": "Receiving.Integrations.ErpConnectionTimeout",
      "displayName": "Integrations - ERP Connection Timeout",
      "defaultValue": "30",
      "dataType": "Int",
      "scope": "System",
      "permissionLevel": "User",
      "isSensitive": false,
      "validationRules": "Int"
    },
    {
      "category": "Receiving",
      "key": "Receiving.Integrations.RetryFailedSyncs",
      "displayName": "Integrations - Retry Failed Syncs",
      "defaultValue": "true",
      "dataType": "Bool",
      "scope": "System",
      "permissionLevel": "User",
      "isSensitive": false,
      "validationRules": "Bool"
    },
    {
      "category": "Receiving",
      "key": "Receiving.Integrations.MaxSyncRetries",
      "displayName": "Integrations - Max Sync Retries",
      "defaultValue": "3",
      "dataType": "Int",
      "scope": "System",
      "permissionLevel": "User",
      "isSensitive": false,
      "validationRules": "Int"
    },
    {
      "category": "Receiving",
      "key": "Receiving.PartNumberPadding.Enabled",
      "displayName": "Part Number Padding - Enabled",
      "defaultValue": "true",
      "dataType": "Bool",
      "scope": "System",
      "permissionLevel": "User",
      "isSensitive": false,
      "validationRules": "Bool"
    },
    {
      "category": "Receiving",
      "key": "Receiving.PartNumberPadding.RulesJson",
      "displayName": "Part Number Padding - Rules JSON",
      "defaultValue": "[{\"Prefix\":\"MMC\",\"MaxLength\":10,\"PadChar\":\"0\",\"IsEnabled\":true}]",
      "dataType": "String",
      "scope": "System",
      "permissionLevel": "User",
      "isSensitive": false,
      "validationRules": "String"
    }
  ]
}
